{
    "os": "Linux-6.8.0-65-generic-x86_64-with-glibc2.35",
    "python": "3.10.18",
    "heartbeatAt": "2025-08-05T09:59:06.745277",
    "startedAt": "2025-08-05T09:59:05.696983",
    "docker": null,
    "cuda": null,
    "args": null,
    "state": "running",
    "program": "<python with no main file>",
    "git": {
        "remote": "https://github.com/therealtin05/MA-QDax.git",
        "commit": "6656fc5690049649b5281e2379abe4031f4dad50"
    },
    "email": "haidanggacon@gmail.com",
    "root": "/home/tin/Desktop/HaiDang/RL/Mix-ME/MA-QDax",
    "host": "tin-Cyborg-15-A13VFK",
    "username": "tin",
    "executable": "/home/tin/anaconda3/envs/mix-me/bin/python",
    "cpu_count": 10,
    "cpu_count_logical": 16,
    "cpu_freq": {
        "current": 2333.508875,
        "min": 400.0,
        "max": 4475.0
    },
    "cpu_freq_per_core": [
        {
            "current": 400.072,
            "min": 400.0,
            "max": 4700.0
        },
        {
            "current": 400.0,
            "min": 400.0,
            "max": 4700.0
        },
        {
            "current": 400.0,
            "min": 400.0,
            "max": 4700.0
        },
        {
            "current": 400.0,
            "min": 400.0,
            "max": 4700.0
        },
        {
            "current": 4873.696,
            "min": 400.0,
            "max": 4900.0
        },
        {
            "current": 4830.595,
            "min": 400.0,
            "max": 4900.0
        },
        {
            "current": 4433.327,
            "min": 400.0,
            "max": 4900.0
        },
        {
            "current": 3001.471,
            "min": 400.0,
            "max": 4900.0
        },
        {
            "current": 1554.078,
            "min": 400.0,
            "max": 4700.0
        },
        {
            "current": 400.0,
            "min": 400.0,
            "max": 4700.0
        },
        {
            "current": 2797.241,
            "min": 400.0,
            "max": 4700.0
        },
        {
            "current": 4699.726,
            "min": 400.0,
            "max": 4700.0
        },
        {
            "current": 3411.452,
            "min": 400.0,
            "max": 3600.0
        },
        {
            "current": 2565.63,
            "min": 400.0,
            "max": 3600.0
        },
        {
            "current": 3335.641,
            "min": 400.0,
            "max": 3600.0
        },
        {
            "current": 3265.93,
            "min": 400.0,
            "max": 3600.0
        }
    ],
    "disk": {
        "total": 228.63730239868164,
        "used": 205.57693481445312
    },
    "gpu": "NVIDIA GeForce RTX 4060 Laptop GPU",
    "gpu_count": 1,
    "gpu_devices": [
        {
            "name": "NVIDIA GeForce RTX 4060 Laptop GPU",
            "memory_total": 8585740288
        }
    ],
    "memory": {
        "total": 15.326560974121094
    }
}
