{
    "os": "Linux-6.8.0-64-generic-x86_64-with-glibc2.35",
    "python": "3.10.18",
    "heartbeatAt": "2025-07-23T03:23:43.243631",
    "startedAt": "2025-07-23T03:23:42.056365",
    "docker": null,
    "cuda": null,
    "args": null,
    "state": "running",
    "program": "<python with no main file>",
    "git": {
        "remote": "https://github.com/therealtin05/MA-QDax.git",
        "commit": "06b409edd375190a76c452cc49fc195d7d4cc61b"
    },
    "email": "haidanggacon@gmail.com",
    "root": "/home/tin/Desktop/HaiDang/RL/Mix-ME/MA-QDax",
    "host": "tin-Cyborg-15-A13VFK",
    "username": "tin",
    "executable": "/home/tin/anaconda3/envs/mix-me/bin/python",
    "cpu_count": 10,
    "cpu_count_logical": 16,
    "cpu_freq": {
        "current": 2537.0355624999997,
        "min": 400.0,
        "max": 4475.0
    },
    "cpu_freq_per_core": [
        {
            "current": 1870.426,
            "min": 400.0,
            "max": 4700.0
        },
        {
            "current": 400.0,
            "min": 400.0,
            "max": 4700.0
        },
        {
            "current": 4659.347,
            "min": 400.0,
            "max": 4700.0
        },
        {
            "current": 400.0,
            "min": 400.0,
            "max": 4700.0
        },
        {
            "current": 4494.087,
            "min": 400.0,
            "max": 4900.0
        },
        {
            "current": 721.232,
            "min": 400.0,
            "max": 4900.0
        },
        {
            "current": 3685.394,
            "min": 400.0,
            "max": 4900.0
        },
        {
            "current": 400.0,
            "min": 400.0,
            "max": 4900.0
        },
        {
            "current": 1323.947,
            "min": 400.0,
            "max": 4700.0
        },
        {
            "current": 400.0,
            "min": 400.0,
            "max": 4700.0
        },
        {
            "current": 3584.181,
            "min": 400.0,
            "max": 4700.0
        },
        {
            "current": 400.0,
            "min": 400.0,
            "max": 4700.0
        },
        {
            "current": 2328.944,
            "min": 400.0,
            "max": 3600.0
        },
        {
            "current": 3098.676,
            "min": 400.0,
            "max": 3600.0
        },
        {
            "current": 3217.326,
            "min": 400.0,
            "max": 3600.0
        },
        {
            "current": 3230.448,
            "min": 400.0,
            "max": 3600.0
        }
    ],
    "disk": {
        "total": 228.63730239868164,
        "used": 204.86846542358398
    },
    "gpu": "NVIDIA GeForce RTX 4060 Laptop GPU",
    "gpu_count": 1,
    "gpu_devices": [
        {
            "name": "NVIDIA GeForce RTX 4060 Laptop GPU",
            "memory_total": 8585740288
        }
    ],
    "memory": {
        "total": 15.326576232910156
    }
}
